rainbowpy/__init__.py
rainbowpy/_version.py
rainbowpy/colormap.py
rainbowpy/coolors.py
rainbowpy/file_utils.py
rainbowpy/generate_maps_from_config.py
rainbowpy/data/custom_maps.yml
rainbowpy/data/test
rainbowpy-0.4.0.dist-info/LICENSE
rainbowpy-0.4.0.dist-info/METADATA
rainbowpy-0.4.0.dist-info/WHEEL
rainbowpy-0.4.0.dist-info/top_level.txt
rainbowpy-0.4.0.dist-info/RECORD
