Metadata-Version: 2.1
Name: rainbowpy
Version: 0.4.0
Summary: Some tools for making colormaps
Home-page: https://github.com/grburgess/rainbowpy
Author: J. Michael Burgess
Author-email: jmichaelburgess@gmail.com
License: GPL-2+
Project-URL: Bug Tracker, https://github.com/grburgess/rainbowpy/issues
Project-URL: Source Code, https://github.com/grburgess/rainbowpy
Platform: UNKNOWN
Classifier: Development Status :: 2 - Pre-Alpha
Classifier: Environment :: Console
Classifier: Intended Audience :: Science/Research
Classifier: License :: OSI Approved :: GNU General Public License v2 or later (GPLv2+)
Classifier: Operating System :: POSIX
Classifier: Programming Language :: Python :: 3.5
Classifier: Programming Language :: Python :: 3.6
Classifier: Programming Language :: Python :: 3.7
Classifier: Programming Language :: Python :: 3.8
Requires-Dist: numpy
Requires-Dist: matplotlib
Requires-Dist: pyyaml
Requires-Dist: palettable
Requires-Dist: ipythonblocks
